<?xml version="1.0" encoding="UTF-8"?><record_update table="content_block_programmatic">
    <content_block_programmatic action="INSERT_OR_UPDATE">
        <active>true</active>
        <category>general</category>
        <condition/>
        <conditional>false</conditional>
        <frame display_value="frame_grey_border">cf52ad460a0a0b6300321234a7187571</frame>
        <logged_on>false</logged_on>
        <name>Create New Family Cohort Referral Record</name>
        <programmatic_content><![CDATA[<?xml version="1.0" encoding="utf-8" ?>
<j:jelly trim="false" xmlns:j="jelly:core" xmlns:g="glide" xmlns:j2="null" xmlns:g2="null">

	<form>
		<input type="button" value="Click here to create a new Family Cohort Referral" onclick="window.location.href='/uri=%2Fx_naci_family_coho_mock_up_intake.do'" style=" width: 280px; height: 100px; text-align: center" />
	</form>

</j:jelly>]]></programmatic_content>
        <sys_class_name>content_block_programmatic</sys_class_name>
        <sys_created_by>martincp@nih.gov</sys_created_by>
        <sys_created_on>2019-10-16 18:14:13</sys_created_on>
        <sys_customer_update>false</sys_customer_update>
        <sys_id>b1b93695dbac0010b86770c08c961996</sys_id>
        <sys_mod_count>10</sys_mod_count>
        <sys_name>Create New Family Cohort Referral Record</sys_name>
        <sys_package display_value="Family Cohort Study" source="x_naci_family_coho">090e9eb7dba7774054d8ff621f9619eb</sys_package>
        <sys_policy/>
        <sys_replace_on_upgrade>false</sys_replace_on_upgrade>
        <sys_scope display_value="Family Cohort Study">090e9eb7dba7774054d8ff621f9619eb</sys_scope>
        <sys_update_name>content_block_programmatic_b1b93695dbac0010b86770c08c961996</sys_update_name>
        <sys_updated_by>martincp@nih.gov</sys_updated_by>
        <sys_updated_on>2019-10-16 18:51:43</sys_updated_on>
        <two_phase>false</two_phase>
    </content_block_programmatic>
</record_update>
